vrorRCC/__init__.py
vrorRCC/assignment_problem.py
vrorRCC/augmentations.py
vrorRCC/cpm.py
vrorRCC/graphical_method.py
vrorRCC/simplex_method.py
vrorRCC/transportation_problem.py
vrorRCC/vrorRCC.py
vror-0.1.10.dist-info/LICENSE
vror-0.1.10.dist-info/METADATA
vror-0.1.10.dist-info/WHEEL
vror-0.1.10.dist-info/top_level.txt
vror-0.1.10.dist-info/RECORD
