Metadata-Version: 2.1
Name: vror
Version: 0.1.10
Summary: A package for solving various optimization problems. Developed by Ramanujan Computing Centre, Anna University.
Home-page: https://github.com/ragu8/vror
Author: Ragu and Team
Author-email: https.ragu@gmail.com
Classifier: Programming Language :: Python :: 3
Classifier: License :: OSI Approved :: MIT License
Classifier: Operating System :: OS Independent
Requires-Python: >=3.6
License-File: LICENSE
Requires-Dist: networkx
Requires-Dist: matplotlib
Requires-Dist: pandas
Requires-Dist: numpy
Requires-Dist: scipy
